ror_downloader/__init__.py
ror_downloader/__main__.py
ror_downloader/api.py
ror_downloader/cli.py
ror_downloader/py.typed
ror_downloader/version.py
ror_downloader-0.0.4.dist-info/licenses/LICENSE
ror_downloader-0.0.4.dist-info/WHEEL
ror_downloader-0.0.4.dist-info/entry_points.txt
ror_downloader-0.0.4.dist-info/METADATA
ror_downloader-0.0.4.dist-info/RECORD
