Metadata-Version: 2.4
Name: ror_downloader
Version: 0.0.4
Summary: Download and cache the Research Organization Registry (ROR)
Keywords: snekpack,cookiecutter
Author: Charles Tapley Hoyt
Author-email: Charles Tapley Hoyt <cthoyt@gmail.com>
License-File: LICENSE
Classifier: Development Status :: 1 - Planning
Classifier: Environment :: Console
Classifier: Intended Audience :: Developers
Classifier: License :: OSI Approved :: MIT License
Classifier: Operating System :: OS Independent
Classifier: Framework :: Pytest
Classifier: Framework :: tox
Classifier: Framework :: Sphinx
Classifier: Natural Language :: English
Classifier: Programming Language :: Python
Classifier: Programming Language :: Python :: 3.10
Classifier: Programming Language :: Python :: 3.11
Classifier: Programming Language :: Python :: 3.12
Classifier: Programming Language :: Python :: 3.13
Classifier: Programming Language :: Python :: 3.14
Classifier: Programming Language :: Python :: 3 :: Only
Classifier: Typing :: Typed
Requires-Dist: zenodo-client
Requires-Dist: pydantic
Requires-Dist: tqdm
Requires-Dist: click
Maintainer: Charles Tapley Hoyt
Maintainer-email: Charles Tapley Hoyt <cthoyt@gmail.com>
Requires-Python: >=3.10
Project-URL: Bug Tracker, https://github.com/cthoyt/ror-downloader/issues
Project-URL: Homepage, https://github.com/cthoyt/ror-downloader
Project-URL: Repository, https://github.com/cthoyt/ror-downloader.git
Project-URL: Documentation, https://ror_downloader.readthedocs.io
Project-URL: Funding, https://github.com/sponsors/cthoyt
